dct_autoencoder/__init__.py
dct_autoencoder/basis.py
dct_autoencoder/core.py
dct_autoencoder/utils.py
dct_autoencoder/visualization.py
dct_autoencoder-0.2.1.dist-info/LICENSE
dct_autoencoder-0.2.1.dist-info/METADATA
dct_autoencoder-0.2.1.dist-info/WHEEL
dct_autoencoder-0.2.1.dist-info/RECORD
