Metadata-Version: 2.1
Name: dct-autoencoder
Version: 0.2.1
Summary: 
Author: Dariush Bahrami
Author-email: dariushbahrami1993@gmail.com
Requires-Python: >=3.10,<4.0
Classifier: Programming Language :: Python :: 3
Classifier: Programming Language :: Python :: 3.10
Classifier: Programming Language :: Python :: 3.11
Classifier: Programming Language :: Python :: 3.12
Requires-Dist: matplotlib (>=3.9.2,<4.0.0)
Requires-Dist: numpy (>=2.1.1,<3.0.0)
Requires-Dist: torch (>=2.4.1,<3.0.0)
